TextTable/__init__.py
TextTable/texttable.py
pytexttable-0.1.6.dist-info/licenses/LICENSE
pytexttable-0.1.6.dist-info/METADATA
pytexttable-0.1.6.dist-info/WHEEL
pytexttable-0.1.6.dist-info/top_level.txt
pytexttable-0.1.6.dist-info/RECORD
