Metadata-Version: 2.4
Name: PyTextTable
Version: 0.1.6
Summary: A class for drawing table in text console for python in windows or linux
Author-email: Alireza Nikseresht <nikseresht@gmail.com>
License: MIT
Classifier: Programming Language :: Python :: 3
Classifier: License :: OSI Approved :: MIT License
Classifier: Operating System :: OS Independent
Requires-Python: >=3.0
License-File: LICENSE
Dynamic: license-file
